physicellloader/__init__.py
physicellloader/_version.py
physicellloader/pyMCDS.py
physicellloader/pyMCDS_timeseries.py
physicellloader/read_MultiCellDS_xml.py
physicellloader/matlab_example/__init__.py
physicellloader/matlab_example/citation and license.txt
physicellloader/matlab_example/initial_mesh0.mat
physicellloader/matlab_example/output00003696.xml
physicellloader/matlab_example/output00003696_cells.mat
physicellloader/matlab_example/output00003696_cells_physicell.mat
physicellloader/matlab_example/output00003696_microenvironment0.mat
physicellloader/matlab_example/snapshot00003696.svg
physicellloader/plotting/__init__.py
physicellloader/plotting/anim_svg.py
physicellloader/plotting/anim_svg_cycle.py
physicellloader/plotting/anim_svg_substrate.py
physicellloader/plotting/cells3D_fury.py
physicellloader/timeseries_set/__init__.py
physicellloader/timeseries_set/config.xml
physicellloader/timeseries_set/final.xml
physicellloader/timeseries_set/final_cells.mat
physicellloader/timeseries_set/final_cells_physicell.mat
physicellloader/timeseries_set/final_microenvironment0.mat
physicellloader/timeseries_set/initial.xml
physicellloader/timeseries_set/initial_cells.mat
physicellloader/timeseries_set/initial_cells_physicell.mat
physicellloader/timeseries_set/initial_mesh0.mat
physicellloader/timeseries_set/initial_microenvironment0.mat
physicellloader/timeseries_set/output00000000.xml
physicellloader/timeseries_set/output00000000_cells.mat
physicellloader/timeseries_set/output00000000_cells_physicell.mat
physicellloader/timeseries_set/output00000000_microenvironment0.mat
physicellloader/timeseries_set/output00000001.xml
physicellloader/timeseries_set/output00000001_cells.mat
physicellloader/timeseries_set/output00000001_cells_physicell.mat
physicellloader/timeseries_set/output00000001_microenvironment0.mat
physicellloader/timeseries_set/output00000002.xml
physicellloader/timeseries_set/output00000002_cells.mat
physicellloader-1.1.21.dist-info/METADATA
physicellloader-1.1.21.dist-info/WHEEL
physicellloader-1.1.21.dist-info/top_level.txt
physicellloader-1.1.21.dist-info/RECORD
