Metadata-Version: 2.1
Name: physicellloader
Version: 1.1.21
Summary: Python data loader for PhysiCell digital snapshots.
Home-page: https://github.com/PhysiCell-Tools/python-loader
Author: Randy Heiland
Author-email: epbucher@iu.edu
Project-URL: Bug Reports, https://github.com/PhysiCell-Tools/python-loader/issues
Project-URL: Funding, http://www.mathcancer.org/
Project-URL: Say Thanks!, http://physicell.org/
Project-URL: Source, https://github.com/PhysiCell-Tools/python-loader
Keywords: physicell,python3,data analysis
Classifier: Development Status :: 3 - Alpha
Classifier: Intended Audience :: Developers
Classifier: Intended Audience :: Science/Research
Classifier: Topic :: Scientific/Engineering :: Bio-Informatics
Classifier: License :: OSI Approved :: BSD License
Classifier: Programming Language :: Python :: 3 :: Only
Requires-Python: >=3.6, <4
Requires-Dist: matplotlib
Requires-Dist: numpy
Requires-Dist: pandas
